thisworddoesnotexist/__init__.py
thisworddoesnotexist-0.2.3.dist-info/METADATA
thisworddoesnotexist-0.2.3.dist-info/WHEEL
thisworddoesnotexist-0.2.3.dist-info/entry_points.txt
thisworddoesnotexist-0.2.3.dist-info/top_level.txt
thisworddoesnotexist-0.2.3.dist-info/RECORD
