Metadata-Version: 2.4
Name: thisworddoesnotexist
Version: 0.2.3
Summary: Fetch a fake word from thisworddoesnotexist.com
Home-page: https://codeberg.org/poofbirb/thisworddoesnotexist
Author: Poofbirb
Author-email: poofbirb@protonmail.com.com
Classifier: Programming Language :: Python :: 3
Classifier: License :: OSI Approved :: MIT License
Classifier: Operating System :: OS Independent
Requires-Python: >=3.6
Requires-Dist: requests>=2.31.0
Requires-Dist: beautifulsoup4>=4.12.0
Dynamic: author
Dynamic: author-email
Dynamic: classifier
Dynamic: description
Dynamic: description-content-type
Dynamic: home-page
Dynamic: requires-dist
Dynamic: requires-python
Dynamic: summary
